y0/__init__.py
y0/__main__.py
y0/causaleffect.py
y0/cli.py
y0/complexity.py
y0/dsl.py
y0/graph.py
y0/predicates.py
y0/r_utils.py
y0/simulation.py
y0/struct.py
y0/version.py
y0/algorithm/__init__.py
y0/algorithm/conditional_independencies.py
y0/algorithm/falsification.py
y0/algorithm/sigma_separation.py
y0/algorithm/simplify_latent.py
y0/algorithm/taheri_design.py
y0/algorithm/transport.py
y0/algorithm/estimation/__init__.py
y0/algorithm/estimation/linear_scm.py
y0/algorithm/identify/__init__.py
y0/algorithm/identify/_extras.py
y0/algorithm/identify/api.py
y0/algorithm/identify/cg.py
y0/algorithm/identify/id_c.py
y0/algorithm/identify/id_star.py
y0/algorithm/identify/id_std.py
y0/algorithm/identify/idc_star.py
y0/algorithm/identify/utils.py
y0/algorithm/separation/__init__.py
y0/algorithm/separation/sigma_separation.py
y0/examples/__init__.py
y0/examples/backdoor.py
y0/examples/frontdoor.py
y0/examples/frontdoor_backdoor.py
y0/examples/sars.py
y0/examples/smoke_cancer.py
y0/examples/utils.py
y0/mutate/__init__.py
y0/mutate/canonicalize_expr.py
y0/mutate/chain.py
y0/mutate/contract.py
y0/mutate/utils.py
y0/parser/__init__.py
y0/parser/internal.py
y0/parser/ce/__init__.py
y0/parser/ce/grammar.py
y0/parser/ce/utils.py
y0/resources/__init__.py
y0/resources/asia.csv
y0/resources/viral_pathogenesis.json
y0/util/combinatorics.py
y0-0.2.11.dist-info/LICENSE
y0-0.2.11.dist-info/METADATA
y0-0.2.11.dist-info/WHEEL
y0-0.2.11.dist-info/entry_points.txt
y0-0.2.11.dist-info/top_level.txt
y0-0.2.11.dist-info/RECORD
