Metadata-Version: 2.1
Name: y0
Version: 0.2.11
Summary: Python code for causal modeling.
Home-page: https://github.com/y0-causal-inference/y0
Download-URL: https://github.com/y0-causal-inference/y0/releases
Author: Jeremy Zucker
Author-email: jeremy.zucker@pnnl.gov
Maintainer: Charles Tapley Hoyt
Maintainer-email: cthoyt@gmail.com
License: BSD-3-Clause
Project-URL: Bug Tracker, https://github.com/y0-causal-inference/y0/issues
Project-URL: Source Code, https://github.com/y0-causal-inference/y0
Keywords: cthoyt,cookiecutter,structural causal modeling
Classifier: Development Status :: 4 - Beta
Classifier: Environment :: Console
Classifier: Intended Audience :: Developers
Classifier: Intended Audience :: Science/Research
Classifier: License :: OSI Approved :: BSD License
Classifier: Operating System :: OS Independent
Classifier: Programming Language :: Python
Classifier: Programming Language :: Python :: 3.10
Classifier: Programming Language :: Python :: 3.11
Classifier: Programming Language :: Python :: 3 :: Only
Classifier: Topic :: Scientific/Engineering :: Mathematics
Classifier: Topic :: Scientific/Engineering :: Information Analysis
Classifier: Topic :: Software Development :: Compilers
Classifier: Framework :: Pytest
Classifier: Framework :: tox
Classifier: Framework :: Sphinx
Requires-Python: >=3.10
License-File: LICENSE
Requires-Dist: more-itertools
Requires-Dist: tqdm
Requires-Dist: click
Requires-Dist: more-click
Requires-Dist: pyparsing
Requires-Dist: networkx
Requires-Dist: tabulate
Requires-Dist: pandas
Requires-Dist: scikit-learn
Requires-Dist: statsmodels
Provides-Extra: docs
Requires-Dist: sphinx ; extra == 'docs'
Requires-Dist: sphinx-rtd-theme ; extra == 'docs'
Requires-Dist: sphinx-click ; extra == 'docs'
Requires-Dist: sphinx-automodapi ; extra == 'docs'
Requires-Dist: texext ; extra == 'docs'
Provides-Extra: r
Requires-Dist: rpy2 ; extra == 'r'
Provides-Extra: tests
Requires-Dist: pytest ; extra == 'tests'
Requires-Dist: coverage ; extra == 'tests'
Requires-Dist: ananke-causal ; extra == 'tests'
Requires-Dist: pgmpy ; extra == 'tests'
